odoo/addons/account_payment_credit_card/README.rst
odoo/addons/account_payment_credit_card/__init__.py
odoo/addons/account_payment_credit_card/__manifest__.py
odoo/addons/account_payment_credit_card/i18n/account_payment_credit_card.pot
odoo/addons/account_payment_credit_card/models/__init__.py
odoo/addons/account_payment_credit_card/models/account.py
odoo/addons/account_payment_credit_card/models/account_move.py
odoo/addons/account_payment_credit_card/readme/CONFIGURE.rst
odoo/addons/account_payment_credit_card/readme/CONTRIBUTORS.rst
odoo/addons/account_payment_credit_card/readme/DESCRIPTION.rst
odoo/addons/account_payment_credit_card/readme/USAGE.rst
odoo/addons/account_payment_credit_card/static/description/icon.png
odoo/addons/account_payment_credit_card/static/description/index.html
odoo/addons/account_payment_credit_card/views/account_view.xml
odoo12_addon_account_payment_credit_card-12.0.1.0.1.dist-info/METADATA
odoo12_addon_account_payment_credit_card-12.0.1.0.1.dist-info/WHEEL
odoo12_addon_account_payment_credit_card-12.0.1.0.1.dist-info/top_level.txt
odoo12_addon_account_payment_credit_card-12.0.1.0.1.dist-info/RECORD
